<?xml version="1.0"?>
<!--Created by PrimeWave Design Environment (TM), build , on Thu Apr  3 16:00:43 2025-->
<file-format version="1.0" name="stateCategory">
 <collection name="convergenceAids">
  <object version="1" name="convergenceAids" type="saConvergenceAid">
   <attribute name="enabled" type="giBoolean" value="1"/>
   <attribute name="node" type="giString" value="/BLB"/>
   <attribute name="nodeType" type="giString" value="Initial Condition"/>
   <attribute name="voltage" type="giString" value="0.8"/>
  </object>
  <object version="1" name="convergenceAids" type="saConvergenceAid">
   <attribute name="enabled" type="giBoolean" value="1"/>
   <attribute name="node" type="giString" value="/BL"/>
   <attribute name="nodeType" type="giString" value="Initial Condition"/>
   <attribute name="voltage" type="giString" value="0.8"/>
  </object>
  <object version="1" name="convergenceAids" type="saConvergenceAid">
   <attribute name="enabled" type="giBoolean" value="0"/>
   <attribute name="node" type="giString" value="/I0/~Q"/>
   <attribute name="nodeType" type="giString" value="Initial Condition"/>
   <attribute name="voltage" type="giString" value=""/>
  </object>
  <object version="1" name="convergenceAids" type="saConvergenceAid">
   <attribute name="enabled" type="giBoolean" value="1"/>
   <attribute name="node" type="giString" value="/I0/Q"/>
   <attribute name="nodeType" type="giString" value="Initial Condition"/>
   <attribute name="voltage" type="giString" value="0.8"/>
  </object>
 </collection>
</file-format>
