<?xml version="1.0"?>
<!--Created by PrimeWave Design Environment (TM), build , on Sun Apr  6 19:54:10 2025-->
<file-format version="1.0" name="stateCategory">
 <object type="saTimestamps" version="1" name="timestamps">
  <attribute value="" type="giString" name="designData"/>
  <attribute value="0" type="giInt" name="designTimestamp"/>
  <attribute value="" type="giString" name="filterList"/>
  <attribute value="" type="giString" name="includeFilesData"/>
  <attribute value="0" type="giInt" name="lastFullScan"/>
  <attribute value="0" type="giBoolean" name="resultsUpToDate"/>
  <attribute value="" type="giString" name="saeSessionData"/>
 </object>
</file-format>
